tortuemobile/__init__.py
tortuemobile/tortuemobilejs/paper.js
tortuemobile/tortuemobilejs/turtlewidget.js
tortuemobile-0.5.2.dist-info/LICENSE
tortuemobile-0.5.2.dist-info/METADATA
tortuemobile-0.5.2.dist-info/WHEEL
tortuemobile-0.5.2.dist-info/top_level.txt
tortuemobile-0.5.2.dist-info/RECORD
