Metadata-Version: 2.1
Name: tortuemobile
Version: 0.5.2
Summary: Un module pour les tortues dans les cahiers Jupyter.
Home-page: https://github.com/callysto/tortuemobile
Author: David Hay
Author-email: misterhay@gmail.com
Classifier: Framework :: IPython
Classifier: Intended Audience :: Education
Classifier: License :: OSI Approved :: BSD License
Classifier: Programming Language :: Python :: 2
Classifier: Programming Language :: Python :: 3
Classifier: Topic :: Artistic Software
Classifier: Topic :: Education
License-File: LICENSE
Requires-Dist: IPython
Requires-Dist: ipywidgets (>=7.0.0)
